nose_sigterm.py
nose_sigterm-0.1.0.dist-info/DESCRIPTION.rst
nose_sigterm-0.1.0.dist-info/METADATA
nose_sigterm-0.1.0.dist-info/RECORD
nose_sigterm-0.1.0.dist-info/WHEEL
nose_sigterm-0.1.0.dist-info/entry_points.txt
nose_sigterm-0.1.0.dist-info/metadata.json
nose_sigterm-0.1.0.dist-info/top_level.txt
