Metadata-Version: 2.0
Name: nose-sigterm
Version: 0.1.0
Summary: Raise KeyboardInterrupt on SIGTERM
Home-page: https://github.com/scoutexchange/nose-sigterm
Author: UNKNOWN
Author-email: UNKNOWN
License: UNKNOWN
Platform: UNKNOWN
Classifier: Intended Audience :: Developers
Classifier: Topic :: Software Development :: Testing
Classifier: Programming Language :: Python
Requires-Dist: nose
